twitter.common.log-0.3.10-py2.7-nspkg.pth
twitter/common/log/__init__.py
twitter/common/log/handlers.py
twitter/common/log/initialize.py
twitter/common/log/options.py
twitter/common/log/parsers.py
twitter/common/log/reader.py
twitter/common/log/tracer.py
twitter/common/log/formatters/__init__.py
twitter/common/log/formatters/base.py
twitter/common/log/formatters/glog.py
twitter/common/log/formatters/plain.py
twitter.common.log-0.3.10.dist-info/DESCRIPTION.rst
twitter.common.log-0.3.10.dist-info/METADATA
twitter.common.log-0.3.10.dist-info/RECORD
twitter.common.log-0.3.10.dist-info/WHEEL
twitter.common.log-0.3.10.dist-info/metadata.json
twitter.common.log-0.3.10.dist-info/namespace_packages.txt
twitter.common.log-0.3.10.dist-info/top_level.txt
twitter.common.log-0.3.10.dist-info/zip-safe
